bentoml/__init__.py
bentoml/__main__.py
bentoml/_version.py
bentoml/exceptions.py
bentoml/types.py
bentoml/adapters/__init__.py
bentoml/adapters/annotated_image_input.py
bentoml/adapters/base_input.py
bentoml/adapters/base_output.py
bentoml/adapters/clipper_input.py
bentoml/adapters/dataframe_input.py
bentoml/adapters/dataframe_output.py
bentoml/adapters/default_output.py
bentoml/adapters/file_input.py
bentoml/adapters/image_input.py
bentoml/adapters/json_input.py
bentoml/adapters/json_output.py
bentoml/adapters/multi_file_input.py
bentoml/adapters/multi_image_input.py
bentoml/adapters/pytorch_tensor_input.py
bentoml/adapters/string_input.py
bentoml/adapters/tensorflow_tensor_input.py
bentoml/adapters/tensorflow_tensor_output.py
bentoml/adapters/utils.py
bentoml/artifact/__init__.py
bentoml/cli/__init__.py
bentoml/cli/aws_ec2.py
bentoml/cli/aws_lambda.py
bentoml/cli/aws_sagemaker.py
bentoml/cli/azure_functions.py
bentoml/cli/bento_management.py
bentoml/cli/bento_service.py
bentoml/cli/click_utils.py
bentoml/cli/deployment.py
bentoml/cli/utils.py
bentoml/cli/yatai_service.py
bentoml/clipper/__init__.py
bentoml/configuration/__init__.py
bentoml/configuration/containers.py
bentoml/configuration/default_configuration.yml
bentoml/frameworks/__init__.py
bentoml/frameworks/coreml.py
bentoml/frameworks/detectron.py
bentoml/frameworks/easyocr.py
bentoml/frameworks/evalml.py
bentoml/frameworks/fastai.py
bentoml/frameworks/fasttext.py
bentoml/frameworks/gluon.py
bentoml/frameworks/h2o.py
bentoml/frameworks/keras.py
bentoml/frameworks/lightgbm.py
bentoml/frameworks/onnx.py
bentoml/frameworks/onnxmlir.py
bentoml/frameworks/paddle.py
bentoml/frameworks/pytorch.py
bentoml/frameworks/sklearn.py
bentoml/frameworks/spacy.py
bentoml/frameworks/tensorflow.py
bentoml/frameworks/transformers.py
bentoml/frameworks/xgboost.py
bentoml/handlers/__init__.py
bentoml/marshal/__init__.py
bentoml/marshal/dispatcher.py
bentoml/marshal/marshal.py
bentoml/marshal/utils.py
sinaraml_bentoml-0.13.2.2.dist-info/LICENSE
sinaraml_bentoml-0.13.2.2.dist-info/METADATA
sinaraml_bentoml-0.13.2.2.dist-info/WHEEL
sinaraml_bentoml-0.13.2.2.dist-info/entry_points.txt
sinaraml_bentoml-0.13.2.2.dist-info/top_level.txt
sinaraml_bentoml-0.13.2.2.dist-info/RECORD
