Metadata-Version: 2.1
Name: sinaraml-bentoml
Version: 0.13.2.2
Summary: A framework for machine learning model serving
Home-page: UNKNOWN
Author: sinaraml
Author-email: sinaraml.official@gmail.com
License: Apache License 2.0
Platform: UNKNOWN
Classifier: License :: OSI Approved :: Apache Software License
Classifier: Operating System :: OS Independent
Classifier: Programming Language :: Python :: 3.6
Classifier: Programming Language :: Python :: 3.7
Classifier: Programming Language :: Python :: 3.8
Classifier: Programming Language :: Python :: Implementation :: CPython
Classifier: Topic :: Scientific/Engineering :: Artificial Intelligence
Requires-Python: >=3.6.1
License-File: LICENSE
Requires-Dist: aiohttp
Requires-Dist: aiohttp-cors (==0.7.0)
Requires-Dist: alembic
Requires-Dist: boto3
Requires-Dist: cerberus
Requires-Dist: certifi
Requires-Dist: chardet
Requires-Dist: click (>=7.0)
Requires-Dist: configparser
Requires-Dist: deepmerge
Requires-Dist: docker
Requires-Dist: flask
Requires-Dist: grpcio
Requires-Dist: gunicorn
Requires-Dist: humanfriendly
Requires-Dist: numpy
Requires-Dist: packaging
Requires-Dist: prometheus-client
Requires-Dist: protobuf (<=3.21,>=3.8.0)
Requires-Dist: psutil
Requires-Dist: python-dateutil (<3.0.0,>=2.7.3)
Requires-Dist: python-json-logger
Requires-Dist: requests
Requires-Dist: ruamel.yaml (>=0.15.0)
Requires-Dist: schema
Requires-Dist: simple-di (==0.1.0)
Requires-Dist: sqlalchemy-utils (<0.36.8)
Requires-Dist: sqlalchemy (<1.4.0,>=1.3.0)
Requires-Dist: tabulate
Requires-Dist: urllib3
Requires-Dist: contextvars ; python_version < "3.7"
Requires-Dist: dataclasses ; python_version < "3.7"
Provides-Extra: dev
Requires-Dist: aiohttp ; extra == 'dev'
Requires-Dist: aiohttp-cors (==0.7.0) ; extra == 'dev'
Requires-Dist: alembic ; extra == 'dev'
Requires-Dist: black (==19.10b0) ; extra == 'dev'
Requires-Dist: boto3 ; extra == 'dev'
Requires-Dist: cerberus ; extra == 'dev'
Requires-Dist: certifi ; extra == 'dev'
Requires-Dist: chardet ; extra == 'dev'
Requires-Dist: click (>=7.0) ; extra == 'dev'
Requires-Dist: codecov ; extra == 'dev'
Requires-Dist: configparser ; extra == 'dev'
Requires-Dist: coverage (>=4.4) ; extra == 'dev'
Requires-Dist: deepmerge ; extra == 'dev'
Requires-Dist: docker ; extra == 'dev'
Requires-Dist: ecdsa (==0.14) ; extra == 'dev'
Requires-Dist: flake8 (>=3.8.2) ; extra == 'dev'
Requires-Dist: flask ; extra == 'dev'
Requires-Dist: gitpython (>=2.0.2) ; extra == 'dev'
Requires-Dist: grpc-stubs ; extra == 'dev'
Requires-Dist: grpcio ; extra == 'dev'
Requires-Dist: grpcio-reflection (~=1.34.0) ; extra == 'dev'
Requires-Dist: grpcio-tools (~=1.34.0) ; extra == 'dev'
Requires-Dist: gunicorn ; extra == 'dev'
Requires-Dist: humanfriendly ; extra == 'dev'
Requires-Dist: idna (<=2.8) ; extra == 'dev'
Requires-Dist: imageio (<=2.9.0,>=2.5.0) ; extra == 'dev'
Requires-Dist: mock (>=2.0.0) ; extra == 'dev'
Requires-Dist: moto (==1.3.14) ; extra == 'dev'
Requires-Dist: mypy-protobuf ; extra == 'dev'
Requires-Dist: numpy ; extra == 'dev'
Requires-Dist: packaging ; extra == 'dev'
Requires-Dist: pandas ; extra == 'dev'
Requires-Dist: parameterized ; extra == 'dev'
Requires-Dist: prometheus-client ; extra == 'dev'
Requires-Dist: protobuf (<=3.21,>=3.8.0) ; extra == 'dev'
Requires-Dist: psutil ; extra == 'dev'
Requires-Dist: pyenchant ; extra == 'dev'
Requires-Dist: pylint (>=2.5.2) ; extra == 'dev'
Requires-Dist: pylint (>=2.9.3) ; extra == 'dev'
Requires-Dist: pytest-asyncio ; extra == 'dev'
Requires-Dist: pytest-cov (>=2.7.1) ; extra == 'dev'
Requires-Dist: pytest (>=5.4.0) ; extra == 'dev'
Requires-Dist: python-dateutil (<3.0.0,>=2.7.3) ; extra == 'dev'
Requires-Dist: python-json-logger ; extra == 'dev'
Requires-Dist: recommonmark ; extra == 'dev'
Requires-Dist: requests ; extra == 'dev'
Requires-Dist: ruamel.yaml (>=0.15.0) ; extra == 'dev'
Requires-Dist: schema ; extra == 'dev'
Requires-Dist: scikit-learn ; extra == 'dev'
Requires-Dist: setuptools ; extra == 'dev'
Requires-Dist: simple-di (==0.1.0) ; extra == 'dev'
Requires-Dist: sphinx-click ; extra == 'dev'
Requires-Dist: sphinx (<=3.5.4) ; extra == 'dev'
Requires-Dist: sphinx-copybutton ; extra == 'dev'
Requires-Dist: sphinx-rtd-theme ; extra == 'dev'
Requires-Dist: sphinxcontrib-fulltoc ; extra == 'dev'
Requires-Dist: sphinxcontrib-spelling ; extra == 'dev'
Requires-Dist: sqlalchemy-utils (<0.36.8) ; extra == 'dev'
Requires-Dist: sqlalchemy (<1.4.0,>=1.3.0) ; extra == 'dev'
Requires-Dist: tabulate ; extra == 'dev'
Requires-Dist: tox-conda (>=0.2.0) ; extra == 'dev'
Requires-Dist: tox (>=3.12.1) ; extra == 'dev'
Requires-Dist: twine ; extra == 'dev'
Requires-Dist: types-click ; extra == 'dev'
Requires-Dist: types-protobuf (>=0.1.14) ; extra == 'dev'
Requires-Dist: urllib3 ; extra == 'dev'
Requires-Dist: contextvars ; (python_version < "3.7") and extra == 'dev'
Requires-Dist: dataclasses ; (python_version < "3.7") and extra == 'dev'
Provides-Extra: doc_builder
Requires-Dist: pyenchant ; extra == 'doc_builder'
Requires-Dist: recommonmark ; extra == 'doc_builder'
Requires-Dist: sphinx-click ; extra == 'doc_builder'
Requires-Dist: sphinx (<=3.5.4) ; extra == 'doc_builder'
Requires-Dist: sphinx-copybutton ; extra == 'doc_builder'
Requires-Dist: sphinx-rtd-theme ; extra == 'doc_builder'
Requires-Dist: sphinxcontrib-fulltoc ; extra == 'doc_builder'
Requires-Dist: sphinxcontrib-spelling ; extra == 'doc_builder'
Provides-Extra: model_server
Requires-Dist: jaeger-client ; extra == 'model_server'
Requires-Dist: opentracing ; extra == 'model_server'
Requires-Dist: py-zipkin ; extra == 'model_server'
Provides-Extra: test
Requires-Dist: black (==19.10b0) ; extra == 'test'
Requires-Dist: codecov ; extra == 'test'
Requires-Dist: coverage (>=4.4) ; extra == 'test'
Requires-Dist: ecdsa (==0.14) ; extra == 'test'
Requires-Dist: flake8 (>=3.8.2) ; extra == 'test'
Requires-Dist: idna (<=2.8) ; extra == 'test'
Requires-Dist: imageio (<=2.9.0,>=2.5.0) ; extra == 'test'
Requires-Dist: mock (>=2.0.0) ; extra == 'test'
Requires-Dist: moto (==1.3.14) ; extra == 'test'
Requires-Dist: pandas ; extra == 'test'
Requires-Dist: parameterized ; extra == 'test'
Requires-Dist: pylint (>=2.9.3) ; extra == 'test'
Requires-Dist: pytest-asyncio ; extra == 'test'
Requires-Dist: pytest-cov (>=2.7.1) ; extra == 'test'
Requires-Dist: pytest (>=5.4.0) ; extra == 'test'
Requires-Dist: scikit-learn ; extra == 'test'
Provides-Extra: types_stub
Requires-Dist: grpc-stubs ; extra == 'types_stub'
Requires-Dist: mypy-protobuf ; extra == 'types_stub'
Requires-Dist: types-click ; extra == 'types_stub'
Requires-Dist: types-protobuf (>=0.1.14) ; extra == 'types_stub'
Provides-Extra: yatai_service
Requires-Dist: aws-sam-cli (==0.33.1) ; extra == 'yatai_service'
Requires-Dist: azure-cli ; extra == 'yatai_service'
Requires-Dist: google-cloud-storage ; extra == 'yatai_service'
Requires-Dist: grpcio (~=1.34.0) ; extra == 'yatai_service'
Requires-Dist: psycopg2 ; extra == 'yatai_service'
Requires-Dist: psycopg2-binary ; extra == 'yatai_service'
